logs/__init__.py
logs/niv.log
resources/__init__.py
resources/icons/VRT_Icons/VRT_png/VRT_dark_png/FibreOpticBreak-outTray2.png
resources/icons/VRT_Icons/VRT_png/VRT_dark_png/Hub 2.png
resources/icons/VRT_Icons/VRT_png/VRT_dark_png/Router.png
resources/icons/VRT_Icons/VRT_png/VRT_dark_png/Wireless Router.png
resources/icons/VRT_Icons/VRT_png/VRT_dark_png/Workgroup Switch 2.png
resources/icons/VRT_Icons/VRT_png/VRT_dark_png/aegisdatacellcellulardatalogger2.png
resources/icons/VRT_Icons/VRT_png/VRT_dark_png/appliance2.png
resources/icons/VRT_Icons/VRT_png/VRT_dark_png/atmswitch1.png
resources/icons/VRT_Icons/VRT_png/VRT_dark_png/atmswitch2.png
resources/icons/VRT_Icons/VRT_png/VRT_dark_png/authenticationserver2.png
resources/icons/VRT_Icons/VRT_png/VRT_dark_png/cctvcamera2.png
resources/icons/VRT_Icons/VRT_png/VRT_dark_png/cctvcamera4.png
resources/icons/VRT_Icons/VRT_png/VRT_dark_png/communicationsserver.png
resources/icons/VRT_Icons/VRT_png/VRT_dark_png/compactplc2.png
resources/icons/VRT_Icons/VRT_png/VRT_dark_png/dataacquisitionDarkPngscadaserver2.png
resources/icons/VRT_Icons/VRT_png/VRT_dark_png/databaseserver2.png
resources/icons/VRT_Icons/VRT_png/VRT_dark_png/dataloggerrtu2.png
resources/icons/VRT_Icons/VRT_png/VRT_dark_png/desktop2.png
resources/icons/VRT_Icons/VRT_png/VRT_dark_png/desktop4.png
resources/icons/VRT_Icons/VRT_png/VRT_dark_png/dialupmodem2.png
resources/icons/VRT_Icons/VRT_png/VRT_dark_png/directoryserver.png
resources/icons/VRT_Icons/VRT_png/VRT_dark_png/directoryserver2.png
resources/icons/VRT_Icons/VRT_png/VRT_dark_png/documentscanner2.png
resources/icons/VRT_Icons/VRT_png/VRT_dark_png/documentscanner4.png
resources/icons/VRT_Icons/VRT_png/VRT_dark_png/documentscanner6.png
resources/icons/VRT_Icons/VRT_png/VRT_dark_png/documentscanner8.png
resources/icons/VRT_Icons/VRT_png/VRT_dark_png/dreidlaserscanner1.png
resources/icons/VRT_Icons/VRT_png/VRT_dark_png/dreidlaserscanner2.png
resources/icons/VRT_Icons/VRT_png/VRT_dark_png/endusers2.png
niv-1.5.dist-info/LICENSE.md
niv-1.5.dist-info/METADATA
niv-1.5.dist-info/WHEEL
niv-1.5.dist-info/entry_points.txt
niv-1.5.dist-info/top_level.txt
niv-1.5.dist-info/RECORD
