Metadata-Version: 2.1
Name: niv
Version: 1.5
Summary: console application to visualize network infrastructure using YAML files.
Home-page: https://gitlab.rlp.net/top/21s/niv/niv
Author: HS Worms Top
License: UNKNOWN
Keywords: niv,network infrastructure visualisation
Platform: UNKNOWN
Classifier: Programming Language :: Python :: 3
Classifier: License :: OSI Approved :: MIT License
Classifier: Operating System :: OS Independent
Requires-Python: >=
Requires-Dist: graphviz (==0.16)
Requires-Dist: diagrams (==0.19.1)
Requires-Dist: ruamel.yaml (==0.16.13)
Requires-Dist: PyYAML (==5.4.1)
